{"adequate.word":"adequate","adequate.translation[0].definitions[0].definition":"enough in quantity or of a good enough quality for a particular purpose","adequate.translation[0].definitions[0].synonym":"sufficient","adequate.translation[0].definitions[0].opposite":"inadequate","adequate.translation[0].definitions[0].example[0].text":"Farmers have been slow to make adequate provision for their retirement.","adequate.translation[0].definitions[0].example[1].text":"Some creams we tested failed to give adequate protection against UV light.","adequate.translation[0].definitions[0].example[2].text":"The standard of his work is barely adequate.","adequate.translation[0].definitions[0].example[3].text":"The company has yet to provide an adequate explanation for its actions.","adequate.translation[0].definitions[0].example[4].text":"Are the parking facilities adequate for 50 cars?","adequate.translation[0].definitions[0].example[4].note.text":"adequate for","adequate.translation[0].definitions[0].example[5].text":"The lunchtime menu is more than adequate to satisfy the biggest appetite.","adequate.translation[0].definitions[0].example[5].note.text":"adequate to do something","adequate.translation[0].definitions[1].definition":"fairly good but not excellent","adequate.translation[0].definitions[1].example[0].text":"Her performance was adequate but lacked originality."}