{"disaster area.word":"disaster area","disaster area.translation[0].definitions[0].definition":"a place where a flood, storm, fire etc has happened and caused a lot of damage","disaster area.translation[0].definitions[0].example[0].text":"The town was declared a disaster area  (=officially called a disaster area) after the floods.","disaster area.translation[0].definitions[1].definition":"a place that is very untidy or dirty","disaster area.translation[0].definitions[1].example[0].text":"The kitchen is a disaster area."}