{"go public.word":"go public","go public.translation[0].definitions[0].definition":"to tell everyone about something that was secret","go public.translation[0].definitions[0].example[0].text":"The planners are almost ready to go public on the road-building scheme.","go public.translation[0].definitions[0].example[0].note.text":"go public on/with","go public.translation[0].definitions[1].definition":"to become a public company","go public.translation[0].definitions[1].example[0].text":"Many partnerships went public in the 1980s to secure extra capital."}