{"multiple.word":"multiple","multiple.translation[0].definitions[0].definition":"many, or involving many things, people, events etc","multiple.translation[0].definitions[0].example[0].text":"Baxter was rushed to the hospital with multiple stab wounds.","multiple.translation[0].definitions[0].example[1].text":"Having multiple partners increases your risk of sexual diseases.","multiple.translation[0].definitions[0].example[2].text":"His new album includes multiple versions of the same songs.","multiple.translation[1].definitions[0].definition":"a number that contains a smaller number an exact number of times","multiple.translation[1].definitions[0].example[0].text":"20 is a multiple of 5.","multiple.translation[1].definitions[0].example[0].note.text":"multiple of","multiple.translation[1].definitions[1].definition":"a multiple store","multiple.translation[2].definitions[0].definition":"including or involving many things, people, events etc","multiple.translation[2].definitions[0].example[0].text":"They are investigating the company for multiple violations of trade-practices law.","multiple.translation[2].definitions[0].example[1].text":"They can access multiple databases simultaneously.","multiple.translation[3].definitions[0].definition":"a number which is the result of multiplying a particular number by another number","multiple.translation[3].definitions[0].example[0].text":"The bank will offer multiples of up to four times your income  (=will lend you an amount which is up to four times your yearly income).","multiple.translation[3].definitions[1].definition":"a group or number of a particular product, share etc","multiple.translation[3].definitions[1].example[0].text":"The shares are sold in multiples of 200.","multiple.translation[3].definitions[2].definition":"the price of a share divided by its EARNINGS (=share of a company’s profits for a year)","multiple.translation[3].definitions[2].synonym":"P/E RATIO","multiple.translation[3].definitions[2].example[0].text":"stock that offers low price-earnings multiples, limited risk, and regular dividends","multiple.translation[3].definitions[3].definition":"the rent that a property produces as an investment in relation to the price paid for it","multiple.translation[3].definitions[4].definition":"a company that owns shops trading under the same name in many cities, or one of these shops","multiple.translation[3].definitions[4].synonym":"CHAIN STORE","multiple.translation[3].definitions[4].example[0].text":"We are taking trade from large multiples where service is poor."}