{"bet.word":"bet","bet.translation[0].past_tense":"bet","bet.translation[0].past_participle":"bet","bet.translation[0].definitions[0].definition":"to risk money on the result of a race, game, competition, or other future event","bet.translation[0].definitions[0].example[0].text":"How much do you want to bet?","bet.translation[0].definitions[0].example[1].text":"He bet me £10 that I wouldn’t do it.","bet.translation[0].definitions[0].example[1].note.text":"bet (somebody) that","bet.translation[0].definitions[0].example[2].text":"She bet all her money on a horse that came last.","bet.translation[0].definitions[0].example[2].note.text":"bet (something) on something","bet.translation[0].definitions[0].example[3].text":"I wouldn’t bet against him winning the championship this year.","bet.translation[0].definitions[0].example[3].note.text":"bet against","bet.translation[1].definitions[0].definition":"an agreement to risk money on the result of a race, game etc or on something happening, or the money that you risk","bet.translation[1].definitions[0].example[0].text":"a £50 bet","bet.translation[1].definitions[0].example[1].text":"Bookmakers are already taking bets on the outcome.","bet.translation[1].definitions[0].example[2].text":"We placed bets on three horses.","bet.translation[1].definitions[0].example[2].note.text":"place/put/lay a bet","bet.translation[1].definitions[0].example[3].text":"If he scores now, I’ll win my bet.","bet.translation[1].definitions[0].example[3].note.text":"win/lose a bet","bet.translation[1].definitions[0].example[4].text":"A few of us had a bet on who’d get married first.","bet.translation[1].definitions[0].example[4].note.text":"bet on","bet.translation[1].note_box[0].sections[0].items[0].collocation":"have a bet","bet.translation[1].note_box[0].sections[0].items[0].example[0].text":"Are you going to have a bet on the race?","bet.translation[1].note_box[0].sections[0].items[1].collocation":"place/put/lay a bet on something","bet.translation[1].note_box[0].sections[0].items[1].example[0].text":"She placed a bet on a horse called Beethoven.","bet.translation[1].note_box[0].sections[0].items[2].collocation":"take a bet","bet.translation[1].note_box[0].sections[0].items[2].example[0].text":"They're taking bets on the result of the election now.","bet.translation[1].note_box[0].sections[0].items[3].collocation":"win a bet","bet.translation[1].note_box[0].sections[0].items[3].example[0].text":"France won the game and I won my bet.","bet.translation[1].note_box[0].sections[0].items[4].collocation":"lose a bet","bet.translation[1].note_box[0].sections[0].items[4].example[0].text":"If I have a bet, I always lose it.","bet.translation[1].note_box[0].sections[0].items[5].collocation":"make a bet","bet.translation[1].note_box[0].sections[0].items[5].example[0].text":"If you want to make money on the stock market, you have to start making bets.","bet.translation[2].past_tense":"bet","bet.translation[2].past_participle":"bet","bet.translation[2].definitions[0].definition":"to risk money on a future event, for example by investing in a company or product or buying stocks or shares","bet.translation[2].definitions[0].example[0].text":"Investors were willing to bet on the company, and its shares jumped $1.94 to $9.06.","bet.translation[2].definitions[0].example[0].note.text":"bet (something) on","bet.translation[2].definitions[0].example[1].text":"The New Jersey fund has bet $40 million on small stocks.","bet.translation[2].definitions[0].example[1].note.text":"bet (something) on","bet.translation[2].definitions[0].example[2].text":"The market bet heavily that the dollar would fall.","bet.translation[2].definitions[0].example[2].note.text":"bet (somebody) that","bet.translation[2].definitions[1].definition":"to risk a lot of money on a future event, for example by investing in a company or product or buying stocks or shares","bet.translation[2].definitions[1].example[0].text":"Do we really want to bet the ranch on this deal?","bet.translation[3].definitions[0].definition":"when you risk money on a future event, for example by investing in a company or product or buying stocks or shares","bet.translation[3].definitions[0].example[0].text":"They like selling short, or making a bet that share prices will decline.","bet.translation[3].definitions[0].example[1].text":"Shearson placed a big bet on junk bonds and lost.","bet.translation[3].definitions[0].example[2].text":"a huge $11 billion bet on US interest rates that went wrong"}