{"groom.word":"groom","groom.translation[0].definitions[0].definition":"a bridegroom","groom.translation[0].definitions[1].definition":"someone whose job is to feed, clean, and take care of horses","groom.translation[1].definitions[0].definition":"to clean and brush an animal, especially a horse","groom.translation[1].definitions[1].definition":"to prepare someone for an important job or position in society by training them over a long period","groom.translation[1].definitions[1].example[0].text":"Tim was being groomed for a managerial position.","groom.translation[1].definitions[1].example[0].note.text":"groom somebody for something","groom.translation[1].definitions[1].example[1].text":"Clare’s been groomed to take her father’s place when he retires.","groom.translation[1].definitions[1].example[1].note.text":"groom somebody to do something","groom.translation[1].definitions[2].definition":"to take care of your own appearance by keeping your hair and clothes clean and tidy","groom.translation[1].definitions[2].example[0].text":"Her hair is always perfectly groomed.","groom.translation[1].definitions[3].definition":"to develop a friendship with a child, with the intention of starting a sexual relationship. This is done by adults, and is illegal when the child is younger than 16.","groom.translation[1].definitions[4].definition":"if an animal grooms itself or another animal, it cleans its own fur and skin or that of the other animal"}