{"insane.word":"insane","insane.translation[0].definitions[0].definition":"completely stupid or crazy, often in a way that is dangerous","insane.translation[0].definitions[0].example[0].text":"That’s an insane risk.","insane.translation[0].definitions[0].example[1].text":"The whole idea sounds absolutely insane to me.","insane.translation[0].definitions[0].example[2].text":"Why did you do that? Have you gone insane?","insane.translation[0].definitions[1].definition":"someone who is insane is permanently and seriously mentally ill so that they cannot live in normal society","insane.translation[0].definitions[1].example[0].text":"The killer was declared criminally insane."}