{"expectation.word":"expectation","expectation.translation[0].definitions[0].definition":"what you think or hope will happen","expectation.translation[0].definitions[0].example[0].text":"Having raised expectations  (=made people more hopeful), he went on to help only a few people.","expectation.translation[0].definitions[0].example[1].text":"The show exceeded all expectations  (=was much better than expected).","expectation.translation[0].definitions[0].example[2].text":"The number of people who attended fell short of expectations  (=was lower than expected).","expectation.translation[0].definitions[0].example[3].text":"His performance did not live up to our expectations  (=was not as good as we expected).","expectation.translation[0].definitions[0].example[3].note.text":"come/live up to (somebody’s) expectations","expectation.translation[0].definitions[0].example[4].text":"For some time he lived with the expectation that he was going to die.","expectation.translation[0].definitions[0].example[4].note.text":"expectation that","expectation.translation[0].definitions[0].example[5].text":"Anne left Germany in the expectation of seeing her family again before very long.","expectation.translation[0].definitions[0].example[5].note.text":"in (the) expectation of something","expectation.translation[0].definitions[0].example[6].text":"Against all expectations, getting up at five is actually easier in winter.","expectation.translation[0].definitions[0].example[6].note.text":"against/contrary to (all) expectations","expectation.translation[0].definitions[0].example[7].text":"Profits are below expectations.","expectation.translation[0].definitions[0].example[7].note.text":"above/below expectations","expectation.translation[0].definitions[0].example[8].text":"Gina has succeeded beyond our expectations.","expectation.translation[0].definitions[0].example[8].note.text":"beyond (somebody’s) expectations","expectation.translation[0].definitions[1].definition":"a feeling or belief about the way something should be or how someone should behave","expectation.translation[0].definitions[1].example[0].text":"Women who have high expectations of marriage are often disappointed.","expectation.translation[0].definitions[1].example[0].note.text":"expectation of","expectation.translation[0].definitions[1].example[1].text":"Some people have totally unrealistic expectations of both medical and nursing staff.","expectation.translation[0].definitions[1].example[1].note.text":"expectation of","expectation.translation[0].note_box[0].sections[0].items[0].example[0].text":"Like most parents, we have high expectations for our children.","expectation.translation[0].note_box[0].sections[0].items[1].example[0].text":"Their expectations of success were pretty low.","expectation.translation[0].note_box[0].sections[0].items[2].collocation":"great expectations","expectation.translation[0].note_box[0].sections[0].items[2].example[0].text":"Emigrants sailed to America with great expectations.","expectation.translation[0].note_box[0].sections[0].items[3].collocation":"reasonable expectations","expectation.translation[0].note_box[0].sections[0].items[3].example[0].text":"It is a difficult operation, but we have reasonable expectations of success.","expectation.translation[0].note_box[0].sections[0].items[4].collocation":"realistic expectations","expectation.translation[0].note_box[0].sections[0].items[4].example[0].text":"The disease is not curable, and patients must have realistic expectations.","expectation.translation[0].note_box[0].sections[0].items[5].collocation":"unreasonable/unrealistic expectations","expectation.translation[0].note_box[0].sections[0].items[5].example[0].text":"I think you had unrealistic expectations of what could be achieved in the time.","expectation.translation[0].note_box[0].sections[0].items[6].collocation":"legitimate expectations","expectation.translation[0].note_box[0].sections[0].items[6].example[0].text":"The men have legitimate expectations of a fair hearing.","expectation.translation[0].note_box[0].sections[0].items[7].collocation":"growing/rising/increased expectations","expectation.translation[0].note_box[0].sections[0].items[7].example[0].text":"China's economy will grow considerably over the next five years, bringing rising expectations of wealth.","expectation.translation[0].note_box[0].sections[0].items[8].collocation":"general/popular/widespread expectations","expectation.translation[0].note_box[0].sections[0].items[8].example[0].text":"The general expectation was for married couples to have children.","expectation.translation[0].note_box[0].sections[0].items[9].collocation":"family/parental expectations","expectation.translation[0].note_box[0].sections[0].items[9].example[0].text":"Parental expectations for a first child tend to be quite high.","expectation.translation[0].note_box[0].sections[0].items[10].collocation":"social expectations","expectation.translation[0].note_box[0].sections[0].items[10].example[0].text":"Social expectations of masculine and feminine behaviour changed drastically during the 1960s and '70s.","expectation.translation[0].note_box[0].sections[0].items[11].collocation":"career expectations","expectation.translation[0].note_box[0].sections[0].items[11].example[0].text":"People with low self-esteem usually have low career expectations.","expectation.translation[0].note_box[0].sections[1].items[0].collocation":"have expectations","expectation.translation[0].note_box[0].sections[1].items[0].example[0].text":"Many migrant workers had high expectations when they arrived, but not anymore.","expectation.translation[0].note_box[0].sections[1].items[1].collocation":"raise somebody's expectations","expectation.translation[0].note_box[0].sections[1].items[1].example[0].text":"Having raised expectations, the government failed to live up to its promises.","expectation.translation[0].note_box[0].sections[1].items[2].collocation":"lower somebody's expectations","expectation.translation[0].note_box[0].sections[1].items[2].example[0].text":"If you can't afford your dream home, you may have to lower your expectations.","expectation.translation[0].note_box[0].sections[1].items[3].collocation":"come up to/live up to somebody's expectations","expectation.translation[0].note_box[0].sections[1].items[3].example[0].text":"The match was boring, and didn't live up to our expectations at all.","expectation.translation[0].note_box[0].sections[1].items[4].collocation":"fulfil/satisfy somebody's expectations","expectation.translation[0].note_box[0].sections[1].items[4].example[0].text":"The band failed to fulfil the fans' expectations.","expectation.translation[0].note_box[0].sections[1].items[5].collocation":"exceed/surpass somebody's expectations","expectation.translation[0].note_box[0].sections[1].items[5].example[0].text":"The holiday exceeded our expectations.","expectation.translation[0].note_box[0].sections[1].items[6].collocation":"fall below/fall short of somebody's expectations","expectation.translation[0].note_box[0].sections[1].items[6].example[0].text":"Our profits last year fell below expectations.","expectation.translation[0].note_box[0].sections[1].items[7].collocation":"create expectations","expectation.translation[0].note_box[0].sections[1].items[7].example[0].text":"The events of the last few weeks have created expectations of an economic recession.","expectation.translation[0].note_box[0].sections[1].items[8].collocation":"confound somebody's expectations","expectation.translation[0].note_box[0].sections[1].items[8].example[0].text":"The play totally confounds the audience's expectations.","expectation.translation[0].note_box[0].sections[2].items[0].collocation":"above expectations","expectation.translation[0].note_box[0].sections[2].items[0].example[0].text":"Economic growth last month was above expectations.","expectation.translation[0].note_box[0].sections[2].items[1].collocation":"below expectations","expectation.translation[0].note_box[0].sections[2].items[1].example[0].text":"Retail sales in December were well below expectations.","expectation.translation[0].note_box[0].sections[2].items[2].collocation":"beyond all expectations","expectation.translation[0].note_box[0].sections[2].items[2].example[0].text":"The task took two months to complete, but it was successful far beyond all expectations.","expectation.translation[0].note_box[0].sections[2].items[3].collocation":"against/contrary to expectations","expectation.translation[0].note_box[0].sections[2].items[3].example[0].text":"Contrary to our expectations, the share price actually increased."}