{"divulge.word":"divulge","divulge.translation[0].definitions[0].definition":"to give someone information that should be secret","divulge.translation[0].definitions[0].synonym":"reveal","divulge.translation[0].definitions[0].example[0].text":"It is not company policy to divulge personal details of employees.","divulge.translation[0].definitions[0].example[0].note.text":"divulge information/secrets/details etc (to somebody)","divulge.translation[0].definitions[0].example[1].text":"Clare divulged that she was recovering from a nervous breakdown.","divulge.translation[0].definitions[0].example[1].note.text":"divulge that","divulge.translation[0].definitions[0].example[2].text":"The Pentagon refused to divulge what type of plane it was.","divulge.translation[0].definitions[0].example[2].note.text":"divulge what/where etc"}