{"might.word":"might","might.translation[0].definitions[0].definition":"if something might happen or might be true, there is a possibility that it may happen or may be true, but you are not at all certain","might.translation[0].definitions[0].example[0].text":"I might be a few minutes late.","might.translation[0].definitions[0].example[1].text":"She might not want to come with us.","might.translation[0].definitions[0].example[2].text":"He might have missed the train.","might.translation[0].definitions[0].example[3].text":"This might well be her last public performance  (=it is fairly likely).","might.translation[0].definitions[0].example[4].text":"One of the guards might easily panic and shoot someone  (=it is likely).","might.translation[0].definitions[1].definition":"used as the past tense of ‘may’ when reporting that someone talked or thought about the possibility of something","might.translation[0].definitions[1].example[0].text":"He might be able to help you.","might.translation[0].definitions[1].example[1].text":"I thought they might have gone home.","might.translation[0].definitions[1].example[2].text":"She was worried that we might get hurt.","might.translation[0].definitions[2].definition":"used to say that something was a possibility in the past but did not actually happen","might.translation[0].definitions[2].example[0].text":"It was terrifying. We might have been killed.","might.translation[0].definitions[3].signpost":"suggesting","might.translation[0].definitions[3].definition":"used to suggest politely what someone should do","might.translation[0].definitions[3].example[0].text":"If you need more information, you might try the Internet.","might.translation[0].definitions[3].example[1].text":"I thought we might go to the new Chinese restaurant on the High Street.","might.translation[0].definitions[3].example[2].text":"It might be a good idea to put those plants in the shade.","might.translation[0].definitions[3].example[3].text":"We’re going to a concert. You might like to come with us.","might.translation[0].definitions[4].signpost":"asking permission","might.translation[0].definitions[4].definition":"used to politely ask for permission to do something","might.translation[0].definitions[4].example[0].text":"Might I borrow your pen?","might.translation[0].definitions[4].example[1].text":"I wonder if I might speak to your son.","might.translation[0].definitions[5].signpost":"asking permission","might.translation[0].definitions[5].definition":"used when reporting that someone asked for permission to do something","might.translation[0].definitions[5].example[0].text":"He asked if he might come in and look around.","might.translation[0].definitions[6].signpost":"somebody should have done something","might.translation[0].definitions[6].definition":"used when you are annoyed because someone has not done something that you think they should do","might.translation[0].definitions[6].example[0].text":"You might at least say thank you.","might.translation[0].definitions[6].example[1].text":"They might have cleaned up before they left.","might.translation[0].definitions[7].signpost":"past purpose","might.translation[0].definitions[7].definition":"used after ‘so that’ or ‘in order that’ to say that someone did something in order to make something else happen or be possible","might.translation[0].definitions[7].example[0].text":"I asked for names and addresses so that I might pass on details to the police.","might.translation[0].definitions[8].signpost":"although","might.translation[0].definitions[8].definition":"used to say that even though something is perhaps true, something different or opposite is also true","might.translation[0].definitions[8].example[0].text":"He might be nearly seventeen but he’s still very immature.","might.translation[0].definitions[8].example[1].text":"Surprising as it might seem, some tourists actually enjoy the British weather.","might.translation[0].definitions[8].example[2].text":"Although she might understand his beliefs, she could not accept them.","might.translation[0].definitions[8].example[3].text":"Try as I might  (=although I tried hard), I couldn’t work out the answer.","might.translation[0].definitions[9].signpost":"formal question","might.translation[0].definitions[9].definition":"used to ask a question in a formal and rather unfriendly way","might.translation[0].definitions[9].example[0].text":"And who might you be, young man?","might.translation[1].definitions[0].definition":"great strength and power","might.translation[1].definitions[0].example[0].text":"two individuals who took on the might of the English legal system","might.translation[1].definitions[0].example[1].text":"He swung the axe again with all his might."}