{"dealings.word":"dealings","dealings.translation[0].definitions[0].definition":"the business activities or relationships that someone is involved in","dealings.translation[0].definitions[0].example[0].text":"his financial dealings","dealings.translation[0].definitions[0].example[1].text":"We’ve had dealings with him in the past.","dealings.translation[0].definitions[0].example[2].text":"She is ruthless in her dealings with competitors.","dealings.translation[0].definitions[0].example[2].note.text":"dealings with"}