{"forgive me.word":"forgive me","forgive me.translation[0].definitions[0].definition":"used when you are going to say or do something that might seem rude or offensive and you want it to seem more polite","forgive me.translation[0].definitions[0].example[0].text":"Forgive me, but I don’t think that is relevant.","forgive me.translation[0].definitions[0].example[1].text":"Forgive me for saying so, but that’s nonsense.","forgive me.translation[0].definitions[0].example[1].note.text":"forgive me for asking/saying etc something","forgive me.translation[0].definitions[0].example[2].text":"Forgive my phoning you so late.","forgive me.translation[0].definitions[0].example[2].note.text":"forgive me for asking/saying etc something"}