{"come to rest.word":"come to rest","come to rest.translation[0].definitions[0].definition":"to stop moving","come to rest.translation[0].definitions[0].example[0].text":"The aircraft skidded across the runway and finally came to rest in a cornfield.","come to rest.translation[0].definitions[1].definition":"if your eyes come to rest on something, you stop looking around and look at that one thing","come to rest.translation[0].definitions[1].example[0].text":"My eyes came to rest on a photograph of a young man.","come to rest.translation[0].definitions[1].example[0].note.text":"come to rest on"}