{"e-commerce.word":"e-commerce","e-commerce.translation[0].definitions[0].definition":"the activity of buying and selling goods and services and doing other business activities using a computer and the Internet","e-commerce.translation[0].definitions[0].example[0].text":"e-commerce applications such as online ticketing and reservations","e-commerce.translation[1].definitions[0].definition":"electronic commerce; the practice of buying and selling goods and services over the Internet","e-commerce.translation[1].definitions[0].synonym":"e-business","e-commerce.translation[1].definitions[0].example[0].text":"a website design agency specializing in e-commerce","e-commerce.translation[1].definitions[0].example[1].text":"e-commerce applications such as online ticketing and reservations"}