{"comment.word":"comment","comment.translation[0].definitions[0].definition":"an opinion that you express about someone or something","comment.translation[0].definitions[0].synonym":"remark","comment.translation[0].definitions[0].note.text":"no comment (=used by people in public life when they do not want to answer questions)","comment.translation[0].definitions[0].example[0].text":"He was fined for making abusive comments to the referee.","comment.translation[0].definitions[0].example[1].text":"his comments about asylum seekers","comment.translation[0].definitions[0].example[1].note.text":"comment on/about","comment.translation[0].definitions[1].definition":"criticism or discussion of something someone has said or done","comment.translation[0].definitions[1].example[0].text":"The speech received much comment in the press.","comment.translation[0].note_box[0].sections[0].items[0].collocation":"make a comment","comment.translation[0].note_box[0].sections[0].items[0].example[0].text":"Everyone was making appreciative comments about the delicious food.","comment.translation[0].note_box[0].sections[0].items[1].collocation":"have a comment","comment.translation[0].note_box[0].sections[0].items[1].example[0].text":"Do you have any comments on that, David?","comment.translation[0].note_box[0].sections[0].items[2].collocation":"pass (a) comment","comment.translation[0].note_box[0].sections[0].items[2].example[0].text":"He looked at my photos but he didn’t pass comment.","comment.translation[0].note_box[0].sections[0].items[3].collocation":"invite comment(s)","comment.translation[0].note_box[0].sections[0].items[3].example[0].text":"The website invites comments from people who visit it.","comment.translation[0].note_box[0].sections[0].items[4].collocation":"welcome comments","comment.translation[0].note_box[0].sections[0].items[4].example[0].text":"We would welcome your comments and suggestions.","comment.translation[0].note_box[0].sections[0].items[5].collocation":"receive comments","comment.translation[0].note_box[0].sections[0].items[5].example[0].text":"It is very helpful to receive comments from the public.","comment.translation[0].note_box[0].sections[1].items[0].collocation":"a brief/quick comment","comment.translation[0].note_box[0].sections[1].items[0].example[0].text":"I just want to make a very brief comment.","comment.translation[0].note_box[0].sections[1].items[1].collocation":"a helpful/constructive comment","comment.translation[0].note_box[0].sections[1].items[1].example[0].text":"Pay close attention to your teacher’s constructive comments.","comment.translation[0].note_box[0].sections[1].items[2].collocation":"a positive/negative comment","comment.translation[0].note_box[0].sections[1].items[2].example[0].text":"There were some very positive comments in the report.","comment.translation[0].note_box[0].sections[1].items[3].collocation":"a critical comment","comment.translation[0].note_box[0].sections[1].items[3].example[0].text":"The school has received critical comments from inspectors.","comment.translation[0].note_box[0].sections[1].items[4].collocation":"(a) fair comment","comment.translation[0].note_box[0].sections[1].items[4].example[0].text":"I accepted as fair comment 90% of what he said.","comment.translation[0].note_box[0].sections[1].items[5].collocation":"a snide comment","comment.translation[0].note_box[0].sections[1].items[5].example[0].text":"She made some really snide comments about you when you weren’t here.","comment.translation[0].note_box[0].sections[1].items[6].collocation":"a disparaging/derogatory comment","comment.translation[0].note_box[0].sections[1].items[6].example[0].text":"Never make disparaging comments about a colleague’s work.","comment.translation[0].note_box[0].sections[1].items[7].collocation":"a scathing/damning comment","comment.translation[0].note_box[0].sections[1].items[7].example[0].text":"There were a lot of scathing comments about the film.","comment.translation[0].note_box[0].sections[1].items[8].collocation":"an appreciative comment","comment.translation[0].note_box[0].sections[1].items[8].example[0].text":"Appreciative comments may improve your staff’s performance.","comment.translation[0].note_box[0].sections[1].items[9].collocation":"a sarcastic comment","comment.translation[0].note_box[0].sections[1].items[9].example[0].text":"I tried to stay calm, despite his sarcastic comments.","comment.translation[0].note_box[0].sections[1].items[10].collocation":"a casual comment","comment.translation[0].note_box[0].sections[1].items[10].example[0].text":"I only made a casual comment about finding the work a bit boring.","comment.translation[0].note_box[0].sections[1].items[11].collocation":"a passing comment","comment.translation[0].note_box[0].sections[1].items[11].example[0].text":"She got upset about a passing comment I made about her clothes.","comment.translation[0].note_box[0].sections[1].items[12].collocation":"a shrewd comment","comment.translation[0].note_box[0].sections[1].items[12].example[0].text":"His newspaper article is always full of shrewd comments.","comment.translation[0].note_box[0].sections[1].items[13].collocation":"a wry comment","comment.translation[0].note_box[0].sections[1].items[13].example[0].text":"‘Perhaps the food could be improved, ’ was the wry comment of one prisoner.","comment.translation[0].note_box[0].sections[1].items[14].collocation":"a bitter comment","comment.translation[0].note_box[0].sections[1].items[14].example[0].text":"Several pensioners passed some bitter comments.","comment.translation[0].note_box[0].sections[1].items[15].collocation":"a public comment","comment.translation[0].note_box[0].sections[1].items[15].example[0].text":"The jury are forbidden from making public comments.","comment.translation[0].note_box[1].sections[0].items[0].display":"comment","comment.translation[0].note_box[1].sections[0].items[0].definition":"something that you say or write in order to give your opinion","comment.translation[0].note_box[1].sections[0].items[0].example[0].text":"Does anyone have any comments?","comment.translation[0].note_box[1].sections[0].items[0].example[1].text":"Readers are invited to send in their comments and suggestions.","comment.translation[0].note_box[1].sections[0].items[1].display":"remark","comment.translation[0].note_box[1].sections[0].items[1].definition":"something that you say","comment.translation[0].note_box[1].sections[0].items[1].example[0].text":"Just ignore them if they start making rude remarks.","comment.translation[0].note_box[1].sections[0].items[1].example[1].text":"I’m not sure what he meant by that last remark.","comment.translation[0].note_box[1].sections[0].items[2].definition":"something that someone mentions about a subject in a discussion, argument, article etc","comment.translation[0].note_box[1].sections[0].items[2].example[0].text":"That’s an interesting point, Steve.","comment.translation[0].note_box[1].sections[0].items[2].example[1].text":"He raises  (=mentions) a number of important points in his paper.","comment.translation[0].note_box[1].sections[0].items[3].display":"observation","comment.translation[0].note_box[1].sections[0].items[3].definition":"a comment in which you say what you think or have noticed about something","comment.translation[0].note_box[1].sections[0].items[3].example[0].text":"Karl Marx made the observation that history repeats itself first as tragedy, second as farce.","comment.translation[0].note_box[1].sections[0].items[4].display":"aside","comment.translation[0].note_box[1].sections[0].items[4].definition":"a comment made in a low voice, that you intend only certain people to hear","comment.translation[0].note_box[1].sections[0].items[4].example[0].text":"‘Is that true?’ she whispered in an aside to Don.","comment.translation[0].note_box[1].sections[0].items[5].display":"quip","comment.translation[0].note_box[1].sections[0].items[5].definition":"a clever and amusing comment","comment.translation[0].note_box[1].sections[0].items[5].example[0].text":"She knew she should reply with some light-hearted quip.","comment.translation[0].note_box[1].sections[0].items[6].display":"dig","comment.translation[0].note_box[1].sections[0].items[6].definition":"a comment you make to annoy or criticize someone","comment.translation[0].note_box[1].sections[0].items[6].example[0].text":"I’m tired of her little digs at me.","comment.translation[0].note_box[1].sections[0].items[7].display":"taunt","comment.translation[0].note_box[1].sections[0].items[7].definition":"a comment intended to make someone angry or upset","comment.translation[0].note_box[1].sections[0].items[7].example[0].text":"The fans made racist taunts throughout the game.","comment.translation[1].definitions[0].definition":"to express an opinion about someone or something","comment.translation[1].definitions[0].synonym":"remark","comment.translation[1].definitions[0].example[0].text":"People were always commenting on his size.","comment.translation[1].definitions[0].example[0].note.text":"comment on","comment.translation[1].definitions[0].example[1].text":"Smith’s lawyer commented that the decision was ‘outrageous’.","comment.translation[1].definitions[0].example[1].note.text":"comment that"}