{"next to.word":"next to","next to.translation[0].definitions[0].definition":"very close to someone or something, with no other person, building, place etc in between","next to.translation[0].definitions[0].example[0].text":"There was a little girl sitting next to him.","next to.translation[0].definitions[1].definition":"used to give a list of things you like, hate etc in order to say what is first on the list","next to.translation[0].definitions[1].example[0].text":"Next to soccer, I like playing tennis best.","next to.translation[0].definitions[2].definition":"in comparison with someone or something","next to.translation[0].definitions[2].example[0].text":"Next to her, I’m a very poor cook.","next to.translation[0].note_box[0].sections[0].items[0].display":"next to","next to.translation[0].note_box[0].sections[0].items[0].definition":"very close to someone or something, with no other person, building, place etc in between","next to.translation[0].note_box[0].sections[0].items[0].example[0].text":"I sat next to him at dinner.","next to.translation[0].note_box[0].sections[0].items[0].example[1].text":"The hotel was right next to the airport.","next to.translation[0].note_box[0].sections[0].items[1].display":"beside","next to.translation[0].note_box[0].sections[0].items[1].definition":"next to the side of someone or something","next to.translation[0].note_box[0].sections[0].items[1].example[0].text":"Ella came and sat down beside me.","next to.translation[0].note_box[0].sections[0].items[1].example[1].text":"They were sitting beside the pool.","next to.translation[0].note_box[0].sections[0].items[2].display":"by","next to.translation[0].note_box[0].sections[0].items[2].definition":"next to something – often used about being very close to a window, door, or the edge of something such as an area of water","next to.translation[0].note_box[0].sections[0].items[2].example[0].text":"I saw him standing by the window.","next to.translation[0].note_box[0].sections[0].items[2].example[1].text":"Weymouth is a pretty little town by the sea.","next to.translation[0].note_box[0].sections[0].items[2].example[2].text":"She lives by the river.","next to.translation[0].note_box[0].sections[0].items[3].display":"next door","next to.translation[0].note_box[0].sections[0].items[3].definition":"in the building or room next to yours, or next to another one","next to.translation[0].note_box[0].sections[0].items[3].example[0].text":"The house next door is much bigger than ours.","next to.translation[0].note_box[0].sections[0].items[3].example[1].text":"Have you met the people who’ve just moved in next door?","next to.translation[0].note_box[0].sections[0].items[4].display":"alongside","next to.translation[0].note_box[0].sections[0].items[4].definition":"close to the side of something, especially a river, railway, boat, or vehicle","next to.translation[0].note_box[0].sections[0].items[4].example[0].text":"I decided to take the path alongside the railway track.","next to.translation[0].note_box[0].sections[0].items[4].example[1].text":"A police car pulled up alongside.","next to.translation[0].note_box[0].sections[0].items[5].display":"adjacent","next to.translation[0].note_box[0].sections[0].items[5].definition":"a building, room, or piece of land that is adjacent to another one is next to it","next to.translation[0].note_box[0].sections[0].items[5].example[0].text":"They walked through a rose garden adjacent to the hospital.","next to.translation[0].note_box[0].sections[0].items[5].example[1].text":"The blaze spread to two adjacent buildings.","next to.translation[0].note_box[0].sections[0].items[6].display":"adjoining","next to.translation[0].note_box[0].sections[0].items[6].definition":"an adjoining room, building, or piece of land is one that is next to another one and is joined to it","next to.translation[0].note_box[0].sections[0].items[6].example[0].text":"We had adjoining rooms at the hotel."}