{"rummage.word":"rummage","rummage.translation[0].definitions[0].definition":"to search for something by moving things around in a careless or hurried way","rummage.translation[0].definitions[0].example[0].text":"Looks like someone’s been rummaging around in my desk.","rummage.translation[0].definitions[0].example[0].note.text":"rummage in/through etc","rummage.translation[1].definitions[0].definition":"a careless or hurried search for something","rummage.translation[1].definitions[0].example[0].text":"Have a rummage in my jewellery box and see if you can find something you like.","rummage.translation[1].definitions[1].definition":"old clothes, toys etc that you no longer want"}