{"persecute.word":"persecute","persecute.translation[0].definitions[0].definition":"to treat someone cruelly or unfairly over a period of time, especially because of their religious or political beliefs","persecute.translation[0].definitions[0].example[0].text":"The Puritans left England to escape being persecuted.","persecute.translation[0].definitions[1].definition":"to deliberately cause difficulties for someone by annoying them often","persecute.translation[0].definitions[1].synonym":"harass","persecute.translation[0].definitions[1].example[0].text":"Like many celebrities, she complained of being persecuted by the press."}