{"train.translation[0].definitions[0].signpost":"railway","train.translation[0].definitions[0].definition":"a set of several carriages that are connected to each other and pulled along a railway line by an engine","train.translation[0].definitions[0].example[0].text":"the train to Munich","train.translation[0].definitions[0].example[0].note.text":"train to","train.translation[0].definitions[0].example[1].text":"We went all the way to Inverness by train.","train.translation[0].definitions[0].example[1].note.text":"by train","train.translation[0].definitions[1].signpost":"people/animals","train.translation[0].definitions[1].definition":"a long line of moving people, animals, or vehicles","train.translation[0].definitions[1].example[0].text":"a camel train","train.translation[0].definitions[2].signpost":"dress","train.translation[0].definitions[2].definition":"a part of a long dress that spreads out over the ground behind the person wearing it","train.translation[0].definitions[2].example[0].text":"a wedding dress with a long train","train.translation[0].definitions[3].signpost":"servants","train.translation[0].definitions[3].definition":"a group of servants or officers following an important person, especially in the past","train.translation[0].note_box[0].sections[0].items[0].collocation":"take/get a train","train.translation[0].note_box[0].sections[0].items[0].example[0].text":"I took the first train home.","train.translation[0].note_box[0].sections[0].items[1].collocation":"catch a train","train.translation[0].note_box[0].sections[0].items[1].example[0].text":"He was in a hurry to catch a train.","train.translation[0].note_box[0].sections[0].items[2].collocation":"go by/travel by train","train.translation[0].note_box[0].sections[0].items[2].example[0].text":"We decided to go by train.","train.translation[0].note_box[0].sections[0].items[3].collocation":"get on/board a train","train.translation[0].note_box[0].sections[0].items[3].example[0].text":"At Stoke, another passenger boarded the train.","train.translation[0].note_box[0].sections[0].items[4].collocation":"get off a train","train.translation[0].note_box[0].sections[0].items[4].example[0].text":"He got off the train at Flushing.","train.translation[0].note_box[0].sections[0].items[5].collocation":"wait for a train","train.translation[0].note_box[0].sections[0].items[5].example[0].text":"She sat on the railway platform for half an hour, waiting for a train.","train.translation[0].note_box[0].sections[0].items[6].collocation":"miss a train","train.translation[0].note_box[0].sections[0].items[6].example[0].text":"I just missed the last train.","train.translation[0].note_box[0].sections[0].items[7].collocation":"trains run","train.translation[0].note_box[0].sections[0].items[7].example[0].text":"Trains run from two main London stations, Victoria and Charing Cross, every hour.","train.translation[0].note_box[0].sections[0].items[8].collocation":"a train arrives","train.translation[0].note_box[0].sections[0].items[8].example[0].text":"The train arrived on time.","train.translation[0].note_box[0].sections[0].items[9].collocation":"a train leaves/departs","train.translation[0].note_box[0].sections[0].items[9].example[0].text":"Trains depart from Rugby at half-hourly intervals until 4.00 pm.","train.translation[0].note_box[0].sections[0].items[10].collocation":"a train pulls into/out of a station","train.translation[0].note_box[0].sections[0].items[10].example[0].text":"The train pulled into Euston station and I got off.","train.translation[0].note_box[0].sections[0].items[11].collocation":"a train derails/is derailed","train.translation[0].note_box[0].sections[0].items[11].example[0].text":"Most of the passengers escaped injury when their train was derailed.","train.translation[0].note_box[0].sections[1].form":"ADJECTIVES/NOUN + train","train.translation[0].note_box[0].sections[1].items[0].collocation":"a freight/goods train","train.translation[0].note_box[0].sections[1].items[0].example[0].text":"a freight train carrying hazardous chemicals","train.translation[0].note_box[0].sections[1].items[1].collocation":"a passenger train","train.translation[0].note_box[0].sections[1].items[1].example[0].text":"a passenger train bound for Geneva","train.translation[0].note_box[0].sections[1].items[2].collocation":"a commuter train","train.translation[0].note_box[0].sections[1].items[2].example[0].text":"a crash involving two crowded commuter trains","train.translation[0].note_box[0].sections[1].items[3].collocation":"an express train/a fast train","train.translation[0].note_box[0].sections[1].items[3].example[0].text":"He boarded the express train to London.","train.translation[0].note_box[0].sections[1].items[4].collocation":"a slow train","train.translation[0].note_box[0].sections[1].items[4].example[0].text":"We got on the stopping train by mistake and it took hours to get home.","train.translation[0].note_box[0].sections[1].items[5].collocation":"a steam train","train.translation[0].note_box[0].sections[1].items[5].example[0].text":"Railway enthusiasts have the opportunity to take a nostalgic trip on a steam train.","train.translation[0].note_box[0].sections[1].items[6].collocation":"a tube/underground train","train.translation[0].note_box[0].sections[1].items[6].example[0].text":"The condition of many tube trains is a disgrace.","train.translation[0].note_box[0].sections[2].form":"train + NOUN","train.translation[0].note_box[0].sections[2].items[0].collocation":"a train journey","train.translation[0].note_box[0].sections[2].items[0].example[0].text":"They were not looking forward to the long train journey.","train.translation[0].note_box[0].sections[2].items[1].collocation":"a train fare","train.translation[0].note_box[0].sections[2].items[1].example[0].text":"How much is the train fare to Derby?","train.translation[0].note_box[0].sections[2].items[2].collocation":"a train driver","train.translation[0].note_box[0].sections[2].items[2].example[0].text":"The train driver apologized for the late departure.","train.translation[0].note_box[0].sections[2].items[3].collocation":"a train crash","train.translation[0].note_box[0].sections[2].items[3].example[0].text":"Ten people were killed in the train crash.","train.translation[0].note_box[1].heading":"GRAMMAR: Patterns with train","train.translation[0].note_box[1].items[0].explanation":"You usually say get on a train","train.translation[0].note_box[1].items[0].example[0].text":"I got on the train at Bristol","train.translation[0].note_box[1].items[1].explanation":"You usually say get off a train","train.translation[0].note_box[1].items[1].example[0].text":"She got off the train in Geneva","train.translation[0].note_box[1].items[2].explanation":"You say that someone is on a train","train.translation[0].note_box[1].items[2].example[0].text":"There were a lot of tourists on the train","train.translation[0].note_box[1].items[3].explanation":"You go somewhere by train","train.translation[0].note_box[1].items[3].example[0].text":"He travels to work by train","train.translation[0].note_box[1].items[3].bad_example[0].text":"go by the train","train.translation[0].note_box[1].items[3].bad_example[1].text":"travel by the train","train.translation[0].note_box[1].items[4].explanation":"You often talk about the train","train.translation[0].note_box[1].items[4].example[0].text":"It’s easier if you take the train","train.translation[1].definitions[0].signpost":"teach somebody","train.translation[1].definitions[0].definition":"to teach someone the skills of a particular job or activity, or to be taught these skills","train.translation[1].definitions[0].example[0].text":"a highly trained workforce","train.translation[1].definitions[0].example[1].text":"Trained staff will be available to deal with your queries.","train.translation[1].definitions[0].example[2].text":"All staff will be trained in customer service skills.","train.translation[1].definitions[0].example[2].note.text":"train somebody in something","train.translation[1].definitions[0].example[3].text":"She’s training to be a doctor.","train.translation[1].definitions[0].example[3].note.text":"train to do something","train.translation[1].definitions[0].example[4].text":"Employees are trained to deal with emergency situations.","train.translation[1].definitions[0].example[4].note.text":"train somebody to do something","train.translation[1].definitions[0].example[5].text":"Nadia trained as a singer.","train.translation[1].definitions[0].example[5].note.text":"train as","train.translation[1].definitions[1].signpost":"teach an animal","train.translation[1].definitions[1].definition":"to teach an animal to do something or to behave correctly","train.translation[1].definitions[1].example[0].text":"a well-trained puppy","train.translation[1].definitions[1].example[1].text":"These dogs are trained to detect drugs.","train.translation[1].definitions[1].example[1].note.text":"train something to do something","train.translation[1].definitions[2].signpost":"prepare for sport","train.translation[1].definitions[2].definition":"to prepare for a sports event or tell someone how to prepare for it, especially by exercising","train.translation[1].definitions[2].example[0].text":"Brenda spends two hours a day training for the marathon.","train.translation[1].definitions[2].example[0].note.text":"train for","train.translation[1].definitions[3].signpost":"aim something","train.translation[1].definitions[3].definition":"to aim something such as a gun or camera at someone or something","train.translation[1].definitions[3].example[0].text":"She trained her binoculars on the bird.","train.translation[1].definitions[3].example[0].note.text":"train something on/at somebody/something","train.translation[1].definitions[4].signpost":"develop something","train.translation[1].definitions[4].definition":"to develop and improve a natural ability or quality","train.translation[1].definitions[4].example[0].text":"You can train your mind to relax.","train.translation[1].definitions[4].example[1].text":"To the trained eye the difference between these flowers is obvious  (=the difference is clear to someone who has developed skills to notice something).","train.translation[1].definitions[5].definition":"to make a plant grow in a particular direction by bending, cutting, or tying it","train.translation[2].definitions[0].definition":"a number of connected carriages pulled by an engine on a railway line","train.translation[3].definitions[0].definition":"to teach someone or to be taught the skills and knowledge needed for a particular job","train.translation[3].definitions[0].example[0].text":"Both my sons want to train as chartered accountants.","train.translation[3].definitions[0].example[1].text":"One of the major costs of implementing the technology was the need to train workers in new skills.","train.translation[3].definitions[0].example[1].note.text":"train somebody in something","train.translation[3].definitions[0].example[2].text":"He trains his people to identify customer needs clearly.","train.translation[3].definitions[0].example[2].note.text":"train somebody to do something"}