{"morally.word":"morally","morally.translation[0].definitions[0].definition":"according to moral principles about what is right and wrong","morally.translation[0].definitions[0].example[0].text":"What you did wasn’t illegal, but it was morally wrong.","morally.translation[0].definitions[0].example[1].text":"There is a belief that village life is somehow morally superior to city life.","morally.translation[0].definitions[0].example[2].text":"Such hypocrisy is morally indefensible.","morally.translation[0].definitions[0].example[3].text":"The Constitution is not morally neutral but is based on certain central values."}