{"get by.word":"get by","get by.translation[0].definitions[0].definition":"to have enough money to buy the things you need, but no more","get by.translation[0].definitions[0].example[0].text":"I don’t earn a huge salary, but we get by.","get by.translation[0].definitions[0].example[1].text":"Sometimes they had to get by on very little.","get by.translation[1].definitions[0].definition":"to manage to deal with a difficult situation, using whatever money, equipment etc you have","get by.translation[1].definitions[0].synonym":"manage","get by.translation[1].definitions[0].example[0].text":"The Fed made several changes designed to make it easier for banks to get by on fewer reserves.","get by.translation[1].definitions[0].example[0].note.text":" on/with","get by.translation[1].definitions[0].example[1].text":"In Microsoft Windows, you can get by with just 2 megabytes of memory.","get by.translation[1].definitions[0].example[1].note.text":" on/with"}