{"global.word":"global","global.translation[0].definitions[0].definition":"affecting or including the whole world","global.translation[0].definitions[0].example[0].text":"global climate change","global.translation[0].definitions[0].example[1].text":"the global economy","global.translation[0].definitions[1].definition":"considering all the parts of a problem or situation together","global.translation[0].definitions[1].example[0].text":"We are taking a global view of our business.","global.translation[0].definitions[2].definition":"affecting a whole computer system, program, or file","global.translation[1].definitions[0].definition":"including and considering all the parts of a situation together, rather than the individual parts separately","global.translation[1].definitions[0].example[0].text":"The auditor’s report takes a global view of the figures.","global.translation[1].definitions[1].definition":"affecting or involving the whole world","global.translation[1].definitions[1].example[0].text":"Information and money are becoming increasingly global.","global.translation[1].definitions[1].example[1].text":"Global banks must be able to serve the financing needs of corporations, big and small, anywhere in the world.","global.translation[1].definitions[1].example[2].text":"We need to reduce operating costs in the face of increased global competition.","global.translation[1].definitions[1].example[3].text":"The US competes in a global market and can’t ignore interest rates in other countries.","global.translation[1].definitions[2].definition":"if a company or industry goes global, it starts doing business all over the world","global.translation[1].definitions[2].example[0].text":"The design agency went global in the 90s and today deals with all the Japanese, German and U.S. car makers."}