{"facilitator.word":"facilitator","facilitator.translation[0].definitions[0].definition":"someone who helps a group of people discuss things with each other or do something effectively","facilitator.translation[0].definitions[1].definition":"something that helps a process to take place","facilitator.translation[1].definitions[0].definition":"someone who helps a group of people discuss things with each other or do something effectively","facilitator.translation[1].definitions[0].example[0].text":"We see our role as facilitators who can get the negotiations going."}